sharepoint_to_df/__init__.py
sharepoint_to_df/sharepoint_utils.py
sharepoint_to_df-0.5.0.dist-info/METADATA
sharepoint_to_df-0.5.0.dist-info/WHEEL
sharepoint_to_df-0.5.0.dist-info/top_level.txt
sharepoint_to_df-0.5.0.dist-info/RECORD
